tahrir_api/__init__.py
tahrir_api/dbapi.py
tahrir_api/migrations/README
tahrir_api/migrations/alembic.ini
tahrir_api/migrations/env.py
tahrir_api/migrations/script.py.mako
tahrir_api/migrations/versions/139ec7ed17b7_add_a_rank_column_to.py
tahrir_api/migrations/versions/16943d9088cf_fix_foreign_key_mism.py
tahrir_api/migrations/versions/24282792d72a_add_created_by_field.py
tahrir_api/migrations/versions/2879ed5a6297_issued_for.py
tahrir_api/migrations/versions/39583332f4ea_add_profile_fields_t.py
tahrir_api/migrations/versions/3c7fd5b4e2c2_add_two_new_columns_.py
tahrir_api/migrations/versions/3d3fb9e59e7b_add_person_avatar.py
tahrir_api/migrations/versions/4099fa344171_add_last_login.py
tahrir_api/migrations/versions/420c02357a1b_add_created_on_field.py
tahrir_api/migrations/versions/459d4cc47d13_add_index_on_assertions_issued_on_column.py
tahrir_api/migrations/versions/508367dcbbb5_add_an_stl_column_fo.py
tahrir_api/migrations/versions/51261da641fb_currentvalue.py
tahrir_api/migrations/versions/5791a2b9fb6a_add_tags_field_to_ba.py
tahrir_api/migrations/versions/ce541796a7_add_authz_table.py
tahrir_api/migrations/versions/e7040e76728_create_new_tables_for_quest.py
tahrir_api/migrations/versions/fa1d309e8c3_add_created_on_field.py
tahrir_api/model.py
tahrir_api/scripts/__init__.py
tahrir_api/scripts/populate_avatars.py
tahrir_api/scripts/populateseries.py
tahrir_api/scripts/syncdb.py
tahrir_api/scripts/utils.py
tahrir_api/utils.py
tahrir_api-1.4.3.dist-info/METADATA
tahrir_api-1.4.3.dist-info/WHEEL
tahrir_api-1.4.3.dist-info/entry_points.txt
tahrir_api-1.4.3.dist-info/licenses/LICENSE
tahrir_api-1.4.3.dist-info/RECORD
