Metadata-Version: 2.4
Name: tahrir-api
Version: 1.4.3
Summary: An API for interacting with the Tahrir database
License: GPLv3+
License-File: LICENSE
Author: Ross Delinger
Author-email: rdelinge@redhat.com
Requires-Python: >=3.9.0,<4.0.0
Classifier: License :: OSI Approved :: GNU General Public License v3 or later (GPLv3+)
Classifier: License :: Other/Proprietary License
Classifier: Programming Language :: Python
Classifier: Programming Language :: Python :: 3
Classifier: Programming Language :: Python :: 3.9
Classifier: Programming Language :: Python :: 3.10
Classifier: Programming Language :: Python :: 3.11
Classifier: Programming Language :: Python :: 3.12
Classifier: Programming Language :: Python :: 3.13
Classifier: Programming Language :: Python :: 3.14
Classifier: Topic :: Internet :: WWW/HTTP
Provides-Extra: scripts
Requires-Dist: alembic (>=1.13.1,<2.0.0)
Requires-Dist: arrow (>=1.3.0,<2.0.0)
Requires-Dist: click (>=8.0.0,<9.0.0) ; extra == "scripts"
Requires-Dist: fasjson-client (>=1.0.8,<2.0.0) ; extra == "scripts"
Requires-Dist: fedora-messaging (>=3.5.0,<4.0.0)
Requires-Dist: pygments (>=2.17.2,<3.0.0)
Requires-Dist: simplejson (>=3.19.2,<4.0.0)
Requires-Dist: sqlalchemy (>=2.0.29,<3.0.0)
Requires-Dist: sqlalchemy-helpers (>=0.13.0)
Requires-Dist: tahrir-messages (>=1.0.2,<3.0.0)
Project-URL: Homepage, https://github.com/fedora-infra/tahrir-api
Project-URL: Repository, https://github.com/fedora-infra/tahrir-api
